README.txt
setup.py
validate_yaml.egg-info/PKG-INFO
validate_yaml.egg-info/SOURCES.txt
validate_yaml.egg-info/dependency_links.txt
validate_yaml.egg-info/entry_points.txt
validate_yaml.egg-info/not-zip-safe
validate_yaml.egg-info/requires.txt
validate_yaml.egg-info/top_level.txt
validateyaml/__init__.py
validateyaml/main.py