Metadata-Version: 1.0
Name: validate-yaml
Version: 0.0
Summary: validate yaml
Home-page: UNKNOWN
Author: Jeff Hammel
Author-email: k0scist@gmail.com
License: UNKNOWN
Platform: UNKNOWN
